puresnmp_olt/__init__.py
puresnmp_olt/accions.py
puresnmp_olt/test.py
puresnmp_olt/tools.py
puresnmp_olt-0.0.18.dist-info/licenses/LICENSE
puresnmp_olt-0.0.18.dist-info/METADATA
puresnmp_olt-0.0.18.dist-info/WHEEL
puresnmp_olt-0.0.18.dist-info/top_level.txt
puresnmp_olt-0.0.18.dist-info/RECORD
